kcapi/__init__.py
kcapi/oid.py
kcapi/sso.py
kcapi/ie/__init__.py
kcapi/ie/auth_flows.py
kcapi/ie/flows_publisher.py
kcapi/rest/__init__.py
kcapi/rest/auth_flows.py
kcapi/rest/client_scopes.py
kcapi/rest/clients.py
kcapi/rest/crud.py
kcapi/rest/groups.py
kcapi/rest/helper.py
kcapi/rest/idp.py
kcapi/rest/realms.py
kcapi/rest/recovery.py
kcapi/rest/resp.py
kcapi/rest/roles.py
kcapi/rest/targets.py
kcapi/rest/url.py
kcapi/rest/users.py
kcapi-1.1.2.dist-info/LICENSE
kcapi-1.1.2.dist-info/METADATA
kcapi-1.1.2.dist-info/WHEEL
kcapi-1.1.2.dist-info/top_level.txt
kcapi-1.1.2.dist-info/RECORD
