Metadata-Version: 2.1
Name: kcapi
Version: 1.1.2
Summary: A module to automate stuff in Keycloak.
Home-page: https://github.com/cesarvr/keycloak-api
Author: cesar valdez
Author-email: cesar <cesar.valdez@gosub.biz>
License: MIT
Project-URL: Homepage, https://github.com/cesarvr/keycloak-api
Project-URL: Bug Tracker, https://github.com/cesarvr/keycloak-api/issues
Classifier: Operating System :: OS Independent
Classifier: License :: OSI Approved :: MIT License
Classifier: Programming Language :: Python :: 3
Requires-Python: >=3.7
License-File: LICENSE
Requires-Dist: requests
